datajet/__init__.py
datajet/_data_map_helpers.py
datajet/_datamap.py
datajet/_normalization.py
datajet/_validations.py
datajet/common_resolvers.py
datajet/datajet.py
datajet/exceptions.py
datajet/keywords.py
datajet-0.2.0.dist-info/LICENSE
datajet-0.2.0.dist-info/METADATA
datajet-0.2.0.dist-info/WHEEL
datajet-0.2.0.dist-info/RECORD
