Metadata-Version: 2.1
Name: datajet
Version: 0.2.0
Summary: A Data Dependency Graph Framework and Executor
Home-page: https://github.com/bmritz/datajet
Author: Brian Ritz
Author-email: brianmritz@gmail.com
Requires-Python: >=3.8,<3.12
Classifier: Programming Language :: Python :: 3
Classifier: Programming Language :: Python :: 3.8
Classifier: Programming Language :: Python :: 3.9
Classifier: Programming Language :: Python :: 3.10
Classifier: Programming Language :: Python :: 3.11
Project-URL: Documentation, https://bmritz.github.io/datajet/
Project-URL: Repository, https://github.com/bmritz/datajet
